{
  "success": true,
  "vote": {
    "id": 31,
    "item_number": "16",
    "title": "16.Award a Purchase Order to Econolite Control Products, Inc. in an Amount of \n$94,720 (Bid No. 23-176) (Non -General Fund) ",
    "description": "epartment(s): Public Works Agency \nRecommended Action: Authorize a one-time purchase and payment of purchase \norder to Econolite Control Products, Inc. for ten assembled traffic signal controller \ncabinets in an amount of $94,720 plus a contingency of $5,000, for a total amount \nnot to exceed $99,720. ",
    "outcome": "PASS",
    "ayes": 7,
    "noes": 0,
    "abstain": 0,
    "absent": 0,
    "meeting_id": 6,
    "meeting_date": "2024-02-20",
    "meeting_type": "regular",
    "member_votes": [
      {
        "member_id": 5,
        "full_name": "Benjamin Vazquez",
        "vote_choice": "AYE"
      },
      {
        "member_id": 4,
        "full_name": "David Penaloza",
        "vote_choice": "AYE"
      },
      {
        "member_id": 3,
        "full_name": "Jessie Lopez",
        "vote_choice": "AYE"
      },
      {
        "member_id": 2,
        "full_name": "Johnathan Ryan Hernandez",
        "vote_choice": "AYE"
      },
      {
        "member_id": 7,
        "full_name": "Phil Bacerra",
        "vote_choice": "AYE"
      },
      {
        "member_id": 6,
        "full_name": "Thai Viet Phan",
        "vote_choice": "AYE"
      },
      {
        "member_id": 1,
        "full_name": "Valerie Amezcua",
        "vote_choice": "AYE"
      }
    ]
  }
}